{"tasks":[{"title":"Read the dialogues. Choose the correct words","questions":[{"title":" — Good morning! Am I late?\n - Morning! No, you are not","multiline":false,"words":[{"title":"—","isActive":false,"id":"template_word1109","options":[{"title":"","id":"option_template_word11091110"}]},{"title":"Good","isActive":false,"id":"template_word1111","options":[{"title":"","id":"option_template_word11111112"}]},{"title":"morning!","isActive":false,"id":"template_word1113","options":[{"title":"","id":"option_template_word11131114"}]},{"title":"Am I","isActive":true,"id":"template_word1115","options":[{"title":"Are","id":"option_template_word11151140"},{"title":"Is","id":"option_template_word11151148"}]},{"title":"late?\n","isActive":false,"id":"template_word1119","options":[{"title":"","id":"option_template_word11191120"}]},{"title":"-","isActive":false,"id":"template_word1121","options":[{"title":"","id":"option_template_word11211122"}]},{"title":"Morning!","isActive":false,"id":"template_word1123","options":[{"title":"","id":"option_template_word11231124"}]},{"title":"No,","isActive":false,"id":"template_word1125","options":[{"title":"","id":"option_template_word11251126"}]},{"title":"you","isActive":false,"id":"template_word1127","options":[{"title":"","id":"option_template_word11271128"}]},{"title":"are not","isActive":true,"id":"template_word1129","options":[{"title":"are","id":"option_template_word11291133"}]}],"id":"template_question_46"},{"title":"- Where is Mike from? Is he from England? \n- No, he isn't. He is from Canada.","multiline":false,"words":[{"title":"-","isActive":false,"id":"template_word3163","options":[{"title":"","id":"option_template_word31633164"}]},{"title":"Where","isActive":false,"id":"template_word3165","options":[{"title":"","id":"option_template_word31653166"}]},{"title":"is","isActive":true,"id":"template_word3167","options":[{"title":"am","id":"option_template_word31673197"}]},{"title":"Mike","isActive":false,"id":"template_word3169","options":[{"title":"","id":"option_template_word31693170"}]},{"title":"from?","isActive":false,"id":"template_word3171","options":[{"title":"","id":"option_template_word31713172"}]},{"title":"Is","isActive":true,"id":"template_word3173","options":[{"title":"are","id":"option_template_word31733198"}]},{"title":"he","isActive":false,"id":"template_word3175","options":[{"title":"","id":"option_template_word31753176"}]},{"title":"from","isActive":false,"id":"template_word3177","options":[{"title":"","id":"option_template_word31773178"}]},{"title":"England?","isActive":false,"id":"template_word3179","options":[{"title":"","id":"option_template_word31793180"}]},{"title":"\n-","isActive":false,"id":"template_word3181","options":[{"title":"","id":"option_template_word31813182"}]},{"title":"No,","isActive":false,"id":"template_word3183","options":[{"title":"","id":"option_template_word31833184"}]},{"title":"he","isActive":false,"id":"template_word3185","options":[{"title":"","id":"option_template_word31853186"}]},{"title":"isn't.","isActive":true,"id":"template_word3187","options":[{"title":"is","id":"option_template_word31873199"}]},{"title":"He","isActive":false,"id":"template_word3189","options":[{"title":"","id":"option_template_word31893190"}]},{"title":"is","isActive":true,"id":"template_word3191","options":[{"title":"are","id":"option_template_word31913200"}]},{"title":"from","isActive":false,"id":"template_word3193","options":[{"title":"","id":"option_template_word31933194"}]},{"title":"Canada.","isActive":false,"id":"template_word3195","options":[{"title":"","id":"option_template_word31953196"}]}],"id":"template_question_389"},{"title":"- Excuse me, where is Central Park? \n- It is over there ","multiline":false,"words":[{"title":"-","isActive":false,"id":"template_word4064","options":[{"title":"","id":"option_template_word40644065"}]},{"title":"Excuse","isActive":false,"id":"template_word4066","options":[{"title":"","id":"option_template_word40664067"}]},{"title":"me,","isActive":false,"id":"template_word4068","options":[{"title":"","id":"option_template_word40684069"}]},{"title":"where","isActive":false,"id":"template_word4070","options":[{"title":"","id":"option_template_word40704071"}]},{"title":"is","isActive":true,"id":"template_word4072","options":[{"title":"are","id":"option_template_word40724088"}]},{"title":"Central","isActive":false,"id":"template_word4074","options":[{"title":"","id":"option_template_word40744075"}]},{"title":"Park?","isActive":false,"id":"template_word4076","options":[{"title":"","id":"option_template_word40764077"}]},{"title":"\n-","isActive":false,"id":"template_word4078","options":[{"title":"","id":"option_template_word40784079"}]},{"title":"It","isActive":false,"id":"template_word4080","options":[{"title":"","id":"option_template_word40804081"}]},{"title":"is","isActive":true,"id":"template_word4082","options":[{"title":"am","id":"option_template_word40824089"}]},{"title":"over","isActive":false,"id":"template_word4084","options":[{"title":"","id":"option_template_word40844085"}]},{"title":"there","isActive":false,"id":"template_word4086","options":[{"title":"","id":"option_template_word40864087"}]}],"id":"template_question_3207"},{"title":"- How are your children?\n- They are OK","multiline":false,"words":[{"title":"-","isActive":false,"id":"template_word4433","options":[{"title":"","id":"option_template_word44334434"}]},{"title":"How","isActive":false,"id":"template_word4435","options":[{"title":"","id":"option_template_word44354436"}]},{"title":"are","isActive":true,"id":"template_word4437","options":[{"title":"is","id":"option_template_word44374449"}]},{"title":"your","isActive":false,"id":"template_word4439","options":[{"title":"","id":"option_template_word44394440"}]},{"title":"children?\n-","isActive":false,"id":"template_word4441","options":[{"title":"","id":"option_template_word44414442"}]},{"title":"They","isActive":false,"id":"template_word4443","options":[{"title":"","id":"option_template_word44434444"}]},{"title":"are","isActive":true,"id":"template_word4445","options":[{"title":"am","id":"option_template_word44454450"},{"title":"is","id":"option_template_word44454451"}]},{"title":"OK","isActive":false,"id":"template_word4447","options":[{"title":"","id":"option_template_word44474448"}]}],"id":"template_question_4096"},{"title":"- What is your favorite book? \n- It is Normal People ","multiline":false,"words":[{"title":"-","isActive":false,"id":"template_word5277","options":[{"title":"","id":"option_template_word52775278"}]},{"title":"What","isActive":false,"id":"template_word5279","options":[{"title":"","id":"option_template_word52795280"}]},{"title":"is","isActive":true,"id":"template_word5281","options":[{"title":"are ","id":"option_template_word52815299"},{"title":"am","id":"option_template_word52815300"}]},{"title":"your","isActive":false,"id":"template_word5283","options":[{"title":"","id":"option_template_word52835284"}]},{"title":"favorite","isActive":false,"id":"template_word5285","options":[{"title":"","id":"option_template_word52855286"}]},{"title":"book?","isActive":false,"id":"template_word5287","options":[{"title":"","id":"option_template_word52875288"}]},{"title":"\n-","isActive":false,"id":"template_word5289","options":[{"title":"","id":"option_template_word52895290"}]},{"title":"It","isActive":false,"id":"template_word5291","options":[{"title":"","id":"option_template_word52915292"}]},{"title":"is","isActive":true,"id":"template_word5293","options":[{"title":"are","id":"option_template_word52935301"},{"title":"am","id":"option_template_word52935302"}]},{"title":"Normal","isActive":false,"id":"template_word5295","options":[{"title":"","id":"option_template_word52955296"}]},{"title":"People","isActive":false,"id":"template_word5297","options":[{"title":"","id":"option_template_word52975298"}]}],"id":"template_question_4458"}],"media":[],"type":"DROPDOWN_TEMPLATE","id":"task_391"},{"title":"Answer the question.","questions":[{"title":"Is your country big?","multiline":false,"answers":[{"title":"","isCorrect":true,"id":"template_qtemplate_question_5309_answer_5310"}],"id":"template_question_5309"},{"title":"What is your favorite book?","multiline":false,"answers":[{"title":"","isCorrect":true,"id":"template_qtemplate_question_5311_answer_5312"}],"id":"template_question_5311"},{"title":"What is your favorite kind of sport?","multiline":false,"answers":[{"title":"","isCorrect":true,"id":"template_qtemplate_question_5313_answer_5314"}],"id":"template_question_5313"}],"media":[],"type":"SELECT_TEMPLATE","id":"task_5316"},{"title":"Put am, is, are ","questions":[{"title":"Hi! I am Mary, and this is my friend, Sasha.","multiline":false,"words":[{"title":"Hi!","isActive":false,"id":"template_word5893","options":[{"title":"","id":"option_template_word58935894"}]},{"title":"I","isActive":false,"id":"template_word5895","options":[{"title":"","id":"option_template_word58955926"}]},{"title":"am","isActive":true,"id":"template_word5924","options":[{"title":"","id":"option_template_word59245927"}]},{"title":"Mary,","isActive":false,"id":"template_word5899","options":[{"title":"","id":"option_template_word58995900"}]},{"title":"and","isActive":false,"id":"template_word5901","options":[{"title":"","id":"option_template_word59015902"}]},{"title":"this","isActive":false,"id":"template_word5903","options":[{"title":"","id":"option_template_word59035904"}]},{"title":"is","isActive":true,"id":"template_word5914","options":[{"title":"","id":"option_template_word59145916"}]},{"title":"my","isActive":false,"id":"template_word5907","options":[{"title":"","id":"option_template_word59075908"}]},{"title":"friend,","isActive":false,"id":"template_word5909","options":[{"title":"","id":"option_template_word59095910"}]},{"title":"Sasha.","isActive":false,"id":"template_word5911","options":[{"title":"","id":"option_template_word59115912"}]}],"id":"template_question_5324"},{"title":"We aren't  from Germany, we are from Spain.","multiline":false,"words":[{"title":"We","isActive":false,"id":"template_word6361","options":[{"title":"","id":"option_template_word63616362"}]},{"title":"aren't","isActive":true,"id":"template_word6363","options":[{"title":"","id":"option_template_word63636377"}]},{"title":"from","isActive":false,"id":"template_word6365","options":[{"title":"","id":"option_template_word63656366"}]},{"title":"Germany,","isActive":false,"id":"template_word6367","options":[{"title":"","id":"option_template_word63676368"}]},{"title":"we","isActive":false,"id":"template_word6369","options":[{"title":"","id":"option_template_word63696370"}]},{"title":"are","isActive":true,"id":"template_word6371","options":[{"title":"","id":"option_template_word63716378"}]},{"title":"from","isActive":false,"id":"template_word6373","options":[{"title":"","id":"option_template_word63736374"}]},{"title":"Spain.","isActive":false,"id":"template_word6375","options":[{"title":"","id":"option_template_word63756376"}]}],"id":"template_question_5928"},{"title":"- Where are you from? - I am from Italy, and you?","multiline":false,"words":[{"title":"-","isActive":false,"id":"template_word7694","options":[{"title":"","id":"option_template_word76947695"}]},{"title":"Where","isActive":false,"id":"template_word7696","options":[{"title":"","id":"option_template_word76967697"}]},{"title":"are","isActive":false,"id":"template_word7698","options":[{"title":"","id":"option_template_word76987699"}]},{"title":"you","isActive":false,"id":"template_word7700","options":[{"title":"","id":"option_template_word77007701"}]},{"title":"from?","isActive":false,"id":"template_word7702","options":[{"title":"","id":"option_template_word77027703"}]},{"title":"-","isActive":false,"id":"template_word7704","options":[{"title":"","id":"option_template_word77047705"}]},{"title":"I","isActive":false,"id":"template_word7706","options":[{"title":"","id":"option_template_word77067707"}]},{"title":"am","isActive":false,"id":"template_word7708","options":[{"title":"","id":"option_template_word77087709"}]},{"title":"from","isActive":false,"id":"template_word7710","options":[{"title":"","id":"option_template_word77107711"}]},{"title":"Italy,","isActive":false,"id":"template_word7712","options":[{"title":"","id":"option_template_word77127713"}]},{"title":"and","isActive":false,"id":"template_word7714","options":[{"title":"","id":"option_template_word77147715"}]},{"title":"you?","isActive":false,"id":"template_word7716","options":[{"title":"","id":"option_template_word77167717"}]}],"id":"template_question_6379"},{"title":"Margaret and Nina are friends.","multiline":false,"words":[{"title":"Margaret","isActive":false,"id":"template_word7886","options":[{"title":"","id":"option_template_word78867887"}]},{"title":"and","isActive":false,"id":"template_word7888","options":[{"title":"","id":"option_template_word78887889"}]},{"title":"Nina","isActive":false,"id":"template_word7890","options":[{"title":"","id":"option_template_word78907891"}]},{"title":"are","isActive":true,"id":"template_word7892","options":[{"title":"","id":"option_template_word78927896"}]},{"title":"friends.","isActive":false,"id":"template_word7894","options":[{"title":"","id":"option_template_word78947895"}]}],"id":"template_question_7718"},{"title":"- Is your mother a doctor?\n- No, she is not ","multiline":false,"words":[{"title":"-","isActive":false,"id":"template_word8464","options":[{"title":"","id":"option_template_word84648465"}]},{"title":"Is","isActive":true,"id":"template_word8466","options":[{"title":"","id":"option_template_word84668485"}]},{"title":"your","isActive":false,"id":"template_word8468","options":[{"title":"","id":"option_template_word84688469"}]},{"title":"mother","isActive":false,"id":"template_word8470","options":[{"title":"","id":"option_template_word84708471"}]},{"title":"a","isActive":false,"id":"template_word8472","options":[{"title":"","id":"option_template_word84728473"}]},{"title":"doctor?\n-","isActive":false,"id":"template_word8474","options":[{"title":"","id":"option_template_word84748475"}]},{"title":"No,","isActive":false,"id":"template_word8476","options":[{"title":"","id":"option_template_word84768477"}]},{"title":"she","isActive":false,"id":"template_word8478","options":[{"title":"","id":"option_template_word84788479"}]},{"title":"is","isActive":false,"id":"template_word8480","options":[{"title":"","id":"option_template_word84808481"}]},{"title":"not","isActive":true,"id":"template_word8482","options":[{"title":"","id":"option_template_word84828484"}]}],"id":"template_question_7897"},{"title":"Why are you so late?","multiline":false,"words":[{"title":"Why","isActive":false,"id":"template_word8727","options":[{"title":"","id":"option_template_word87278728"}]},{"title":"are","isActive":true,"id":"template_word8729","options":[{"title":"","id":"option_template_word87298737"}]},{"title":"you","isActive":false,"id":"template_word8731","options":[{"title":"","id":"option_template_word87318732"}]},{"title":"so","isActive":false,"id":"template_word8733","options":[{"title":"","id":"option_template_word87338734"}]},{"title":"late?","isActive":false,"id":"template_word8735","options":[{"title":"","id":"option_template_word87358736"}]}],"id":"template_question_8486"},{"title":"Julia and Thomas are married.","multiline":false,"words":[{"title":"Julia","isActive":false,"id":"template_word8915","options":[{"title":"","id":"option_template_word89158916"}]},{"title":"and","isActive":false,"id":"template_word8917","options":[{"title":"","id":"option_template_word89178918"}]},{"title":"Thomas","isActive":false,"id":"template_word8919","options":[{"title":"","id":"option_template_word89198920"}]},{"title":"are","isActive":true,"id":"template_word8921","options":[{"title":"","id":"option_template_word89218925"}]},{"title":"married.","isActive":false,"id":"template_word8923","options":[{"title":"","id":"option_template_word89238924"}]}],"id":"template_question_8738"},{"title":"Bob is a police officer.","multiline":false,"words":[{"title":"Bob","isActive":false,"id":"template_word9085","options":[{"title":"","id":"option_template_word90859086"}]},{"title":"is","isActive":true,"id":"template_word9087","options":[{"title":"","id":"option_template_word90879095"}]},{"title":"a","isActive":false,"id":"template_word9089","options":[{"title":"","id":"option_template_word90899090"}]},{"title":"police","isActive":false,"id":"template_word9091","options":[{"title":"","id":"option_template_word90919092"}]},{"title":"officer.","isActive":false,"id":"template_word9093","options":[{"title":"","id":"option_template_word90939094"}]}],"id":"template_question_8926"}],"media":[],"type":"FILL_TEMPLATE","id":"task_5918"}],"id":"166263058046419"}
